jzip/__init__.py
tests/__init__.py
jzip-1.0.1.dist-info/LICENCE
jzip-1.0.1.dist-info/METADATA
jzip-1.0.1.dist-info/WHEEL
jzip-1.0.1.dist-info/top_level.txt
jzip-1.0.1.dist-info/RECORD
