Metadata-Version: 2.1
Name: jzip
Version: 1.0.1
Summary: This package provides utilities to work with gzip compressed base64 content.
Home-page: https://github.com/iammrj/JZip
Author: Jilani Shaik
Author-email: iammrj.java@gmail.com
Classifier: Programming Language :: Python :: 3
Classifier: License :: OSI Approved :: MIT License
Classifier: Operating System :: OS Independent
Requires-Python: >=3.6
License-File: LICENCE
